qbt_helper.py
qbt_helper-0.7.dist-info/METADATA
qbt_helper-0.7.dist-info/WHEEL
qbt_helper-0.7.dist-info/entry_points.txt
qbt_helper-0.7.dist-info/licenses/LICENSE
qbt_helper-0.7.dist-info/RECORD
